VLHcalc/__init__.py
vlhcalc-0.2.dist-info/LICENSE.txt
vlhcalc-0.2.dist-info/METADATA
vlhcalc-0.2.dist-info/WHEEL
vlhcalc-0.2.dist-info/top_level.txt
vlhcalc-0.2.dist-info/RECORD
