Metadata-Version: 2.1
Name: vlhcalc
Version: 0.2
Summary: A simple math calculator for: addition, subtraction, multiplication, division, exponents, absolute value, and logarithms.
Home-page: UNKNOWN
Author: Venkatasai Laksh Hanchate
Author-email: laksh.hanchate22@gmail.com
License: UNKNOWN
Platform: UNKNOWN
Classifier: Programming Language :: Python :: 3
Classifier: License :: OSI Approved :: MIT License
Classifier: Operating System :: OS Independent
